prevent_sleep/__init__.py
prevent_sleep/__main__.py
prevent_sleep/install_service.py
prevent_sleep/prevent_sleep.py
prevent_sleep/py.typed
prevent_sleep/checks/__init__.py
prevent_sleep/checks/checker.py
prevent_sleep/checks/nfs_clients.py
prevent_sleep/checks/ssh_clients.py
prevent_sleep/data/prevent-sleep.service
prevent_sleep/inhibitors/__init__.py
prevent_sleep/inhibitors/dbus_inhibit.py
prevent_sleep/inhibitors/systemd_mask.py
prevent_sleep-0.1.1.dist-info/licenses/LICENSE.txt
prevent_sleep-0.1.1.dist-info/METADATA
prevent_sleep-0.1.1.dist-info/WHEEL
prevent_sleep-0.1.1.dist-info/entry_points.txt
prevent_sleep-0.1.1.dist-info/top_level.txt
prevent_sleep-0.1.1.dist-info/zip-safe
prevent_sleep-0.1.1.dist-info/RECORD
