Metadata-Version: 2.4
Name: prevent-sleep
Version: 0.1.1
Summary: Prevent sleep/suspend when there are (active) SSH or NFS clients.
Home-page: https://github.com/lhupfeldt/prevent_sleep.git
Author: Lars Hupfeldt Nielsen
Author-email: lhn@hupfeldtit.dk
License: 'BSD 3-Clause "New" or "Revised" License'
Classifier: Development Status :: 4 - Beta
Classifier: Intended Audience :: Developers
Classifier: Natural Language :: English
Classifier: Operating System :: POSIX :: Linux
Classifier: Programming Language :: Python :: 3.10
Classifier: Programming Language :: Python :: 3.11
Classifier: Programming Language :: Python :: 3.12
Classifier: Topic :: System :: Systems Administration
Classifier: Topic :: System :: Networking :: Monitoring
Requires-Python: >=3.10
License-File: LICENSE.txt
Requires-Dist: psutil>=5.9.5
Requires-Dist: dbus-python>=1.3.2
Provides-Extra: dev
Requires-Dist: nox; extra == "dev"
Dynamic: license-file
